[
  {
    "accNumber": 101,
    "balance": "17004.14",
    "sum of transaction amounts": 17004.14
  },
  {
    "accNumber": 286,
    "balance": "25533.43",
    "sum of transaction amounts": 25533.43
  },
  {
    "accNumber": 255,
    "balance": "29913.6",
    "sum of transaction amounts": 29913.6
  },
  {
    "accNumber": 242,
    "balance": "31705.31",
    "sum of transaction amounts": 31705.310000000005
  },
  {
    "accNumber": 285,
    "balance": "36115.4",
    "sum of transaction amounts": 36115.399999999994
  },
  {
    "accNumber": 280,
    "balance": "45824.72",
    "sum of transaction amounts": 45824.72000000001
  },
  {
    "accNumber": 278,
    "balance": "48434.8",
    "sum of transaction amounts": 48434.79999999999
  },
  {
    "accNumber": 288,
    "balance": "51490.77",
    "sum of transaction amounts": 51490.770000000004
  },
  {
    "accNumber": 283,
    "balance": "52820.66",
    "sum of transaction amounts": 52820.659999999996
  },
  {
    "accNumber": 246,
    "balance": "58063.58",
    "sum of transaction amounts": 58063.58000000001
  }
]